tell_me_again/__init__.py
tell_me_again/dataset.py
tell_me_again/util.py
tell_me_again-0.1.4.dist-info/LICENSE
tell_me_again-0.1.4.dist-info/METADATA
tell_me_again-0.1.4.dist-info/WHEEL
tell_me_again-0.1.4.dist-info/RECORD
