Metadata-Version: 2.1
Name: tell-me-again
Version: 0.1.4
Summary: Dataset for the paper 'Tell me again! A Large-Scale Dataset of Multiple Summaries for the
License: MIT
Author: Same Story
Requires-Python: >=3.11,<4.0
Classifier: License :: OSI Approved :: MIT License
Classifier: Programming Language :: Python :: 3
Classifier: Programming Language :: Python :: 3.11
Classifier: Programming Language :: Python :: 3.12
Requires-Dist: datasets (>=3.0.1,<4.0.0)
Requires-Dist: numpy (>=1.26.4,<2.0.0)
Requires-Dist: platformdirs (>=4.2.0,<5.0.0)
Requires-Dist: requests (>=2.31.0,<3.0.0)
Requires-Dist: tqdm (>=4.66.1,<5.0.0)
